Workbook

Sheet Dashboard
A1: Budget vs. Actual Dashboard
B2: Current Month : | C2: Jan
H3: Variance (Budget vs Actual) Income:
A4: Figures in USD | B4: Budget | C4: Actual | E4: Variance (Absolute) | F4: Variance ( % )
A5: Income
A6: Sales | B6: =INDEX(Budget!$A$4:$N$17,MATCH(Dashboard!$A6,Budget!$A$4:$A$17,0),MATCH(Dashboard!$C$2,Budget!$A$3:$M$3,0)) -> 6500 | C6: =SUMIFS(Actual!E:E,Actual!C:C,TRIM(Dashboard!$A6),Actual!B:B,TRIM(Dashboard!$C$2)) -> 5000 | E6: =C6-B6 -> -1500 | F6: =C6/B6-1 -> -0.23076923
A7: Services | B7: =INDEX(Budget!$A$4:$N$17,MATCH(Dashboard!$A7,Budget!$A$4:$A$17,0),MATCH(Dashboard!$C$2,Budget!$A$3:$M$3,0)) -> 3500 | C7: =SUMIFS(Actual!E:E,Actual!C:C,TRIM(Dashboard!$A7),Actual!B:B,TRIM(Dashboard!$C$2)) -> 2500 | E7: =C7-B7 -> -1000 | F7: =C7/B7-1 -> -0.28571429
A8: Other Income | B8: =INDEX(Budget!$A$4:$N$17,MATCH(Dashboard!$A8,Budget!$A$4:$A$17,0),MATCH(Dashboard!$C$2,Budget!$A$3:$M$3,0)) -> 6500 | C8: =SUMIFS(Actual!E:E,Actual!C:C,TRIM(Dashboard!$A8),Actual!B:B,TRIM(Dashboard!$C$2)) -> 7500 | E8: =C8-B8 -> 1000 | F8: =C8/B8-1 -> 0.15384615
A9: Total Income | B9: =INDEX(Budget!$A$4:$N$17,MATCH(Dashboard!$A9,Budget!$A$4:$A$17,0),MATCH(Dashboard!$C$2,Budget!$A$3:$M$3,0)) -> 16500 | C9: =SUM(C6:C8) -> 15000 | E9: =C9-B9 -> -1500 | F9: =C9/B9-1 -> -0.090909091
A11: Expenses
A12: Rent | B12: =INDEX(Budget!$A$4:$N$17,MATCH(Dashboard!$A12,Budget!$A$4:$A$17,0),MATCH(Dashboard!$C$2,Budget!$A$3:$M$3,0)) -> 7000 | C12: =SUMIFS(Actual!E:E,Actual!C:C,TRIM(Dashboard!$A12),Actual!B:B,TRIM(Dashboard!$C$2)) -> 7000 | E12: =B12-C12 -> 0 | F12: =B12/C12-1 -> 0
A13: Utilities | B13: =INDEX(Budget!$A$4:$N$17,MATCH(Dashboard!$A13,Budget!$A$4:$A$17,0),MATCH(Dashboard!$C$2,Budget!$A$3:$M$3,0)) -> 4000 | C13: =SUMIFS(Actual!E:E,Actual!C:C,TRIM(Dashboard!$A13),Actual!B:B,TRIM(Dashboard!$C$2)) -> 4800 | E13: =B13-C13 -> -800 | F13: =B13/C13-1 -> -0.16666667
A14: Transport | B14: =INDEX(Budget!$A$4:$N$17,MATCH(Dashboard!$A14,Budget!$A$4:$A$17,0),MATCH(Dashboard!$C$2,Budget!$A$3:$M$3,0)) -> 2200 | C14: =SUMIFS(Actual!E:E,Actual!C:C,TRIM(Dashboard!$A14),Actual!B:B,TRIM(Dashboard!$C$2)) -> 2000 | E14: =B14-C14 -> 200 | F14: =B14/C14-1 -> 0.1
A15: Marketing | B15: =INDEX(Budget!$A$4:$N$17,MATCH(Dashboard!$A15,Budget!$A$4:$A$17,0),MATCH(Dashboard!$C$2,Budget!$A$3:$M$3,0)) -> 2300 | C15: =SUMIFS(Actual!E:E,Actual!C:C,TRIM(Dashboard!$A15),Actual!B:B,TRIM(Dashboard!$C$2)) -> 2200 | E15: =B15-C15 -> 100 | F15: =B15/C15-1 -> 0.045454545
A16: Business Insurance | B16: =INDEX(Budget!$A$4:$N$17,MATCH(Dashboard!$A16,Budget!$A$4:$A$17,0),MATCH(Dashboard!$C$2,Budget!$A$3:$M$3,0)) -> 1000 | C16: =SUMIFS(Actual!E:E,Actual!C:C,TRIM(Dashboard!$A16),Actual!B:B,TRIM(Dashboard!$C$2)) -> 1000 | E16: =B16-C16 -> 0 | F16: =B16/C16-1 -> 0
A17: Other Expenses | B17: =INDEX(Budget!$A$4:$N$17,MATCH(Dashboard!$A17,Budget!$A$4:$A$17,0),MATCH(Dashboard!$C$2,Budget!$A$3:$M$3,0)) -> 1200 | C17: =SUMIFS(Actual!E:E,Actual!C:C,TRIM(Dashboard!$A17),Actual!B:B,TRIM(Dashboard!$C$2)) -> 3000 | E17: =B17-C17 -> -1800 | F17: =B17/C17-1 -> -0.6 | H17: Expenses:
A18: Total Expenses | B18: =INDEX(Budget!$A$4:$N$17,MATCH(Dashboard!$A18,Budget!$A$4:$A$17,0),MATCH(Dashboard!$C$2,Budget!$A$3:$M$3,0)) -> 17700 | C18: =SUM(C12:C17) -> 20000 | E18: =B18-C18 -> -2300 | F18: =B18/C18-1 -> -0.115
C19: `
A20: Savings | B20: =B9-B18 -> -1200 | C20: =C9-C18 -> -5000 | E20: =C20-B20 -> -3800 | F20: =C20/B20-1 -> 3.1666667

Sheet Budget
A1: Budgeted Income & Expenses 2022
A3: Line Item / Category | B3: Jan | C3: Feb | D3: Mar | E3: Apr | F3: May | G3: Jun | H3: Jul | I3: Aug | J3: Sep | K3: Oct | L3: Nov | M3: Dec | N3: Full Year Total
A4: Income
A5: Sales | B5: 6500 | C5: 6500 | D5: 6500 | E5: 6500 | F5: 6500 | G5: 6500 | H5: 6500 | I5: 6500 | J5: 6500 | K5: 6500 | L5: 6500 | M5: 6500 | N5: 78000
A6: Services | B6: 3500 | C6: 3500 | D6: 3500 | E6: 3500 | F6: 3500 | G6: 3500 | H6: 3500 | I6: 3500 | J6: 3500 | K6: 3500 | L6: 3500 | M6: 3500 | N6: 42000
A7: Other Income | B7: 6500 | C7: 6500 | D7: 6500 | E7: 6500 | F7: 6500 | G7: 6500 | H7: 6500 | I7: 6500 | J7: 6500 | K7: 6500 | L7: 6500 | M7: 6500 | N7: 78000
A8: Total Income | B8: 16500 | C8: 16500 | D8: 16500 | E8: 16500 | F8: 16500 | G8: 16500 | H8: 16500 | I8: 16500 | J8: 16500 | K8: 16500 | L8: 16500 | M8: 16500 | N8: 198000
A10: Expenses
A11: Rent | B11: 7000 | C11: 7000 | D11: 7000 | E11: 7000 | F11: 7000 | G11: 7000 | H11: 7000 | I11: 7000 | J11: 7000 | K11: 7000 | L11: 7000 | M11: 7000 | N11: 84000
A12: Utilities | B12: 4000 | C12: 4000 | D12: 4000 | E12: 4000 | F12: 4000 | G12: 4000 | H12: 4000 | I12: 4000 | J12: 4000 | K12: 4000 | L12: 4000 | M12: 4000 | N12: 48000
A13: Transport | B13: 2200 | C13: 2200 | D13: 2200 | E13: 2200 | F13: 2200 | G13: 2200 | H13: 2200 | I13: 2200 | J13: 2200 | K13: 2200 | L13: 2200 | M13: 2200 | N13: 26400
A14: Marketing | B14: 2300 | C14: 2300 | D14: 2300 | E14: 2300 | F14: 2300 | G14: 2300 | H14: 2300 | I14: 2300 | J14: 2300 | K14: 2300 | L14: 2300 | M14: 2300 | N14: 27600
A15: Business Insurance | B15: 1000 | C15: 1000 | D15: 1000 | E15: 1000 | F15: 1000 | G15: 1000 | H15: 1000 | I15: 1000 | J15: 1000 | K15: 1000 | L15: 1000 | M15: 1000 | N15: 12000
A16: Other Expenses | B16: 1200 | C16: 1200 | D16: 1200 | E16: 1200 | F16: 1200 | G16: 1200 | H16: 1200 | I16: 1200 | J16: 1200 | K16: 1200 | L16: 1200 | M16: 1200 | N16: 14400
A17: Total Expenses | B17: 17700 | C17: 17700 | D17: 17700 | E17: 17700 | F17: 17700 | G17: 17700 | H17: 17700 | I17: 17700 | J17: 17700 | K17: 17700 | L17: 17700 | M17: 17700 | N17: 212400
A19: Savings | B19: =B8-B17 -> -1200 | C19: =C8-C17 -> -1200 | D19: =D8-D17 -> -1200 | E19: =E8-E17 -> -1200 | F19: =F8-F17 -> -1200 | G19: =G8-G17 -> -1200 | H19: =H8-H17 -> -1200 | I19: =I8-I17 -> -1200 | ... N19: =N8-N17 -> -14400
A20: Cumulative Savings | B20: =B19 -> -1200 | C20: =B20+C19 -> -2400 | D20: =C20+D19 -> -3600 | E20: =D20+E19 -> -4800 | F20: =E20+F19 -> -6000 | G20: =F20+G19 -> -7200 | H20: =G20+H19 -> -8400 | I20: =H20+I19 -> -9600 | J20: =I20+J19 -> -10800 | ... M20: =L20+M19 -> -14400

Sheet Actual
A1: Date | B1: Month | C1: Category | D1: Description | E1: Amount
A2: 46023 | B2: Jan | C2: Rent | D2: Mall store space co-rent | E2: 7000
A3: 46023 | B3: Jan | C3: Utilities | D3: Winter heating surge | E3: 4800 | H3: Category
A4: 46023 | B4: Jan | C4: Transport | D4: Transit pass & local delivery | E4: 2000 | H4: Rent
A5: 46030 | B5: Jan | C5: Marketing | D5: New Year promo flyers & social ads | E5: 2200 | H5: Utilities
A6: 46033 | B6: Jan | C6: Business Insurance | D6: Property liability premium | E6: 400 | H6: Transport
A7: 46034 | B7: Jan | C7: Business Insurance | D7: Equipment insurance | E7: 300 | H7: Marketing
A8: 46034 | B8: Jan | C8: Business Insurance | D8: Worker compensation premium | E8: 300 | H8: Business Insurance
A9: 46036 | B9: Jan | C9: Other Expenses | D9: Staff uniform refresh | E9: 3000 | H9: Other Expenses
A10: 46053 | B10: Jan | C10: Services | D10: Grooming commissions | E10: 2500 | H10: Services
A11: 46053 | B11: Jan | C11: Sales | D11: Retail pet food & supplies | E11: 5000 | H11: Sales
A12: 46053 | B12: Jan | C12: Other Income | D12: Daycare & overnight boarding | E12: 7500 | H12: Other Income
A13: 46054 | B13: Feb | C13: Rent | D13: Mall store space co-rent | E13: 7000
A14: 46054 | B14: Feb | C14: Utilities | D14: Standard winter operations | E14: 4500
A15: 46054 | B15: Feb | C15: Transport | D15: Delivery vehicle gas & metro | E15: 2200
A16: 46061 | B16: Feb | C16: Transport | D16: Valentine pet promo campaign | E16: 2300
A17: 46064 | B17: Feb | C17: Business Insurance | D17: Property liability premium | E17: 350
A18: 46065 | B18: Feb | C18: Business Insurance | D18: Equipment insurance | E18: 345
A19: 46065 | B19: Feb | C19: Business Insurance | D19: Worker compensation premium | E19: 400
A20: 46067 | B20: Feb | C20: Other Expenses | D20: Breakroom snacks & supplies | E20: 560
A21: 46081 | B21: Feb | C21: Services | D21: Grooming commissions | E21: 2500
A22: 46081 | B22: Feb | C22: Sales | D22: Retail pet food & supplies | E22: 6600
A23: 46081 | B23: Feb | C23: Other Income | D23: Daycare & overnight boarding | E23: 5000
A24: 46082 | B24: Mar | C24: Rent | D24: Mall store space co-rent | E24: 7000
... A34: 46109 | B34: Mar | C34: Other Income | D34: Daycare & overnight boarding | E34: 7000
